aws_simple_pipeline/__init__.py
aws_simple_pipeline/pipeline_stack.py
tests/__init__.py
tests/helper.py
tests/test_pipeline_stack.py
aws_simple_pipeline-0.1.0.dist-info/LICENSE
aws_simple_pipeline-0.1.0.dist-info/METADATA
aws_simple_pipeline-0.1.0.dist-info/WHEEL
aws_simple_pipeline-0.1.0.dist-info/top_level.txt
aws_simple_pipeline-0.1.0.dist-info/RECORD
