Metadata-Version: 2.1
Name: aws-simple-pipeline
Version: 0.1.0
Summary: A simple AWS CDK Python pipeline
Home-page: https://aws-simple-pipeline.readthedocs.io/
Author: Alessandra Bilardi
Author-email: alessandra.bilardi@gmail.com
License: UNKNOWN
Project-URL: Source, https://github.com/bilardi/aws-simple-pipeline
Project-URL: Bug Reports, https://github.com/bilardi/aws-simple-pipeline/issues
Project-URL: Funding, https://donate.pypi.org
Platform: UNKNOWN
Classifier: Programming Language :: Python :: 3
Classifier: License :: OSI Approved :: MIT License
Classifier: Operating System :: OS Independent
Requires-Python: >=3.6
Requires-Dist: aws-cdk.core (<=1.80.0,>=1.62.0)
